flask_shelve.py
setup.cfg
setup.py
Flask_Shelve.egg-info/PKG-INFO
Flask_Shelve.egg-info/SOURCES.txt
Flask_Shelve.egg-info/dependency_links.txt
Flask_Shelve.egg-info/not-zip-safe
Flask_Shelve.egg-info/requires.txt
Flask_Shelve.egg-info/top_level.txt