Metadata-Version: 1.0
Name: Flask-Shelve
Version: 0.1.1
Summary: Shelve support for Flask
Home-page: https://github.com/jamesls/flask-shelve
Author: James Saryerwinnie
Author-email: jls.npi@gmail.com
License: BSD
Platform: any
Classifier: Development Status :: 4 - Beta
Classifier: Environment :: Web Environment
Classifier: Intended Audience :: Developers
Classifier: License :: OSI Approved :: BSD License
Classifier: Operating System :: OS Independent
Classifier: Programming Language :: Python
Classifier: Topic :: Software Development :: Libraries :: Python Modules
